aws_stepfunction/__init__.py
aws_stepfunction/_version.py
aws_stepfunction/boto.py
aws_stepfunction/choice_rule.py
aws_stepfunction/constant.py
aws_stepfunction/exc.py
aws_stepfunction/logger.py
aws_stepfunction/model.py
aws_stepfunction/state.py
aws_stepfunction/state_machine.py
aws_stepfunction/utils.py
aws_stepfunction/workflow.py
aws_stepfunction/actions/__init__.py
aws_stepfunction/actions/aws_batch.py
aws_stepfunction/actions/aws_ecs.py
aws_stepfunction/actions/aws_glue.py
aws_stepfunction/actions/aws_lambda.py
aws_stepfunction/actions/aws_sns.py
aws_stepfunction/actions/aws_sqs.py
aws_stepfunction/actions/base.py
aws_stepfunction/better_boto/__init__.py
aws_stepfunction/better_boto/state_machine.py
aws_stepfunction/better_boto/tagging.py
aws_stepfunction/better_boto/waiter.py
aws_stepfunction/docs/__init__.py
aws_stepfunction/magic/__init__.py
aws_stepfunction/magic/task.py
aws_stepfunction/tests/__init__.py
aws_stepfunction/tests/boto_ses.py
aws_stepfunction/tests/helper.py
aws_stepfunction/tests/paths.py
aws_stepfunction-0.0.5.dist-info/AUTHORS.rst
aws_stepfunction-0.0.5.dist-info/LICENSE.txt
aws_stepfunction-0.0.5.dist-info/METADATA
aws_stepfunction-0.0.5.dist-info/WHEEL
aws_stepfunction-0.0.5.dist-info/top_level.txt
aws_stepfunction-0.0.5.dist-info/RECORD
