Metadata-Version: 2.1
Name: aws-stepfunction
Version: 0.0.5
Summary: Yet the most developer friendly orchestration tool on AWS.
Home-page: https://github.com/MacHu-GWU/aws_stepfunction-project
Download-URL: https://pypi.python.org/pypi/aws_stepfunction/0.0.5#downloads
Author: Sanhe Hu
Author-email: husanhe@gmail.com
Maintainer: Unknown
License: MIT
Platform: Windows
Platform: MacOS
Platform: Unix
Classifier: Development Status :: 4 - Beta
Classifier: Intended Audience :: Developers
Classifier: License :: OSI Approved :: Apache Software License
Classifier: Natural Language :: English
Classifier: Operating System :: Microsoft :: Windows
Classifier: Operating System :: MacOS
Classifier: Operating System :: Unix
Classifier: Programming Language :: Python
Classifier: Programming Language :: Python :: 3.7
Classifier: Programming Language :: Python :: 3.8
Classifier: Programming Language :: Python :: 3.9
Classifier: Programming Language :: Python :: 3.10
Classifier: Programming Language :: Python :: 3 :: Only
License-File: LICENSE.txt
License-File: AUTHORS.rst
Requires-Dist: attrs (>=21.1.0)
Requires-Dist: sentinel (>=1.0.0)
Requires-Dist: boto-session-manager (>=1.3.1)
Requires-Dist: pathlib-mate (>=1.0.0)
Requires-Dist: aws-console-url (>=0.3.1)
Requires-Dist: iterproxy
Requires-Dist: func-args
Provides-Extra: dev
Requires-Dist: pathlib-mate ; extra == 'dev'
Requires-Dist: twine ; extra == 'dev'
Requires-Dist: wheel ; extra == 'dev'
Requires-Dist: boto3 ; extra == 'dev'
Requires-Dist: s3pathlib (>=1.0.10) ; extra == 'dev'
Requires-Dist: cottonformation (>=0.0.8) ; extra == 'dev'
Provides-Extra: docs
Requires-Dist: sphinx (==4.3.0) ; extra == 'docs'
Requires-Dist: sphinx-inline-tabs (==2021.8.17b10) ; extra == 'docs'
Requires-Dist: sphinx-jinja (==1.1.1) ; extra == 'docs'
Requires-Dist: sphinx-copybutton (==0.4.0) ; extra == 'docs'
Requires-Dist: rstobj (==0.0.7) ; extra == 'docs'
Requires-Dist: nbsphinx (==0.8.9) ; extra == 'docs'
Requires-Dist: docfly (==1.0.2) ; extra == 'docs'
Requires-Dist: furo (==2021.8.31) ; extra == 'docs'
Requires-Dist: IPython ; extra == 'docs'
Provides-Extra: tests
Requires-Dist: pytest ; extra == 'tests'
Requires-Dist: pytest-cov ; extra == 'tests'
Requires-Dist: rich ; extra == 'tests'
Requires-Dist: boto3 ; extra == 'tests'
Requires-Dist: s3pathlib (>=1.0.10) ; extra == 'tests'
Requires-Dist: cottonformation (>=0.0.8) ; extra == 'tests'
